simple_ci.py
simple_ci-0.0.1.dist-info/top_level.txt
simple_ci-0.0.1.dist-info/entry_points.txt
simple_ci-0.0.1.dist-info/METADATA
simple_ci-0.0.1.dist-info/RECORD
simple_ci-0.0.1.dist-info/DESCRIPTION.rst
simple_ci-0.0.1.dist-info/metadata.json
simple_ci-0.0.1.dist-info/WHEEL
