Metadata-Version: 2.0
Name: simple-ci
Version: 0.0.1
Summary: Simple CI may quite possibly be the most simplistic ci server ever created.
Home-page: https://github.com/timothycrosley/simple_ci
Author: Timothy Crosley
Author-email: timothy.crosley@gmail.com
License: MIT
Keywords: Todo,Python,Python3
Platform: UNKNOWN
Classifier: Development Status :: 3 - Alpha
Classifier: Intended Audience :: Developers
Classifier: Natural Language :: English
Classifier: Environment :: Console
Classifier: License :: OSI Approved :: MIT License
Classifier: Programming Language :: Python
Classifier: Programming Language :: Python :: 3
Classifier: Programming Language :: Python :: 3.2
Classifier: Programming Language :: Python :: 3.3
Classifier: Programming Language :: Python :: 3.4
Classifier: Programming Language :: Python :: 3.5
Classifier: Topic :: Utilities
Requires: hug
Requires: hot_redis
Requires: sh
Requires: Pillow
Requires-Dist: hug
Requires-Dist: hot-redis
Requires-Dist: sh
Requires-Dist: Pillow
